odoo10_addon_membership_prorrate-10.0.1.0.0.99.dev7-py3.8-nspkg.pth
odoo/addons/membership_prorrate/README.rst
odoo/addons/membership_prorrate/__init__.py
odoo/addons/membership_prorrate/__manifest__.py
odoo/addons/membership_prorrate/i18n/ar.po
odoo/addons/membership_prorrate/i18n/bs.po
odoo/addons/membership_prorrate/i18n/ca.po
odoo/addons/membership_prorrate/i18n/cs.po
odoo/addons/membership_prorrate/i18n/de.po
odoo/addons/membership_prorrate/i18n/en_GB.po
odoo/addons/membership_prorrate/i18n/es.po
odoo/addons/membership_prorrate/i18n/es_CR.po
odoo/addons/membership_prorrate/i18n/es_EC.po
odoo/addons/membership_prorrate/i18n/es_MX.po
odoo/addons/membership_prorrate/i18n/et.po
odoo/addons/membership_prorrate/i18n/fi.po
odoo/addons/membership_prorrate/i18n/fr.po
odoo/addons/membership_prorrate/i18n/fr_CH.po
odoo/addons/membership_prorrate/i18n/hr.po
odoo/addons/membership_prorrate/i18n/hr_HR.po
odoo/addons/membership_prorrate/i18n/hu.po
odoo/addons/membership_prorrate/i18n/it.po
odoo/addons/membership_prorrate/i18n/ja.po
odoo/addons/membership_prorrate/i18n/lt.po
odoo/addons/membership_prorrate/i18n/membership_prorrate.pot
odoo/addons/membership_prorrate/i18n/mk.po
odoo/addons/membership_prorrate/i18n/mn.po
odoo/addons/membership_prorrate/i18n/nb.po
odoo/addons/membership_prorrate/i18n/nl.po
odoo/addons/membership_prorrate/i18n/nl_BE.po
odoo/addons/membership_prorrate/i18n/nl_NL.po
odoo/addons/membership_prorrate/i18n/pt.po
odoo/addons/membership_prorrate/i18n/pt_BR.po
odoo/addons/membership_prorrate/i18n/pt_PT.po
odoo/addons/membership_prorrate/i18n/ro.po
odoo/addons/membership_prorrate/i18n/ru.po
odoo/addons/membership_prorrate/i18n/sl.po
odoo/addons/membership_prorrate/i18n/sv.po
odoo/addons/membership_prorrate/i18n/tr.po
odoo/addons/membership_prorrate/i18n/tr_TR.po
odoo/addons/membership_prorrate/i18n/vi_VN.po
odoo/addons/membership_prorrate/i18n/zh_CN.po
odoo/addons/membership_prorrate/i18n/zh_TW.po
odoo/addons/membership_prorrate/models/__init__.py
odoo10_addon_membership_prorrate-10.0.1.0.0.99.dev7.dist-info/METADATA
odoo10_addon_membership_prorrate-10.0.1.0.0.99.dev7.dist-info/WHEEL
odoo10_addon_membership_prorrate-10.0.1.0.0.99.dev7.dist-info/namespace_packages.txt
odoo10_addon_membership_prorrate-10.0.1.0.0.99.dev7.dist-info/top_level.txt
odoo10_addon_membership_prorrate-10.0.1.0.0.99.dev7.dist-info/RECORD
